catweazle_register/__init__.py
catweazleregister-1.0.4.dist-info/METADATA
catweazleregister-1.0.4.dist-info/WHEEL
catweazleregister-1.0.4.dist-info/entry_points.txt
catweazleregister-1.0.4.dist-info/licenses/LICENSE.txt
catweazleregister-1.0.4.dist-info/RECORD
