Metadata-Version: 2.4
Name: catweazleregister
Version: 1.0.4
Summary: catweazle, the now forked out register script
Author-email: "Stephan.Schultchen" <stephan.schultchen@gmail.com>
License:                     GNU AFFERO GENERAL PUBLIC LICENSE
License-File: LICENSE.txt
Classifier: Programming Language :: Python
Requires-Python: >=3.4
Requires-Dist: httpx
